skill_issue/__init__.py
skill_issue/skill_issue.py
skill_issue-0.0.1.dist-info/METADATA
skill_issue-0.0.1.dist-info/WHEEL
skill_issue-0.0.1.dist-info/top_level.txt
skill_issue-0.0.1.dist-info/RECORD
