Metadata-Version: 2.1
Name: skill-issue
Version: 0.0.1
Summary: Seriously, if you have to read this, skill issue on your part
Home-page: https://github.com/yourusername/skill-issue
Author: Krish Verma
Author-email: krishverma2004@gmail.com
Classifier: Programming Language :: Python :: 3
Classifier: License :: OSI Approved :: MIT License
Classifier: Operating System :: OS Independent
Requires-Python: >=3.6
